[{"name":"floor 1","amenities":["olympic pool 34","tennis court 46"]},{"name":"floor 2","amenities":["gate 95"]},{"name":"floor 3","amenities":["college 14","heliport 53"]},{"name":"floor 4","amenities":[]},{"name":"floor 5","amenities":[]},{"name":"floor 6","amenities":["olympic pool 12"]},{"name":"floor 7","amenities":[]},{"name":"floor 8","amenities":["tennis court 67"]},{"name":"floor 9","amenities":[]},{"name":"floor 10","amenities":["gym 50"]},{"name":"floor 11","amenities":["university 14"]},{"name":"floor 12","amenities":[]},{"name":"floor 13","amenities":[]},{"name":"floor 14","amenities":[]},{"name":"floor 15","amenities":[]},{"name":"floor 16","amenities":[]},{"name":"floor 17","amenities":["indoor parking 30"]},{"name":"floor 18","amenities":[]},{"name":"floor 19","amenities":["super market 53"]},{"name":"floor 20","amenities":["high school 48","bike parking 51"]},{"name":"floor 21","amenities":[]},{"name":"floor 22","amenities":["gym 71"]},{"name":"floor 23","amenities":[]},{"name":"floor 24","amenities":["pool 80"]},{"name":"floor 25","amenities":["indoor parking 51"]},{"name":"floor 26","amenities":[]},{"name":"floor 27","amenities":[]},{"name":"floor 28","amenities":[]},{"name":"floor 29","amenities":[]},{"name":"floor 30","amenities":["park 81","olympic pool 72"]},{"name":"floor 31","amenities":["high school 93","football field 24"]},{"name":"floor 32","amenities":["voley court 96"]},{"name":"floor 33","amenities":["socker court 34"]},{"name":"floor 34","amenities":[]},{"name":"floor 35","amenities":["olympic pool 42"]},{"name":"floor 36","amenities":["market 75"]},{"name":"floor 37","amenities":["pharmacy 51"]},{"name":"floor 38","amenities":["indoor parking 86"]},{"name":"floor 39","amenities":["middle school 16"]},{"name":"floor 40","amenities":["super market 75"]},{"name":"floor 41","amenities":["gate 15"]},{"name":"floor 42","amenities":["monkey bars 57","ice rink 83"]},{"name":"floor 43","amenities":["visitor parking 93"]},{"name":"floor 44","amenities":[]},{"name":"floor 45","amenities":["covered parking 66","slide 29"]},{"name":"floor 46","amenities":["rest area 75"]},{"name":"floor 47","amenities":[]},{"name":"floor 48","amenities":["covered parking 12"]},{"name":"floor 49","amenities":["gate 9"]},{"name":"floor 50","amenities":["pool 60"]},{"name":"floor 51","amenities":["college 46"]},{"name":"floor 52","amenities":["socker court 18"]},{"name":"floor 53","amenities":["garage 88"]},{"name":"floor 54","amenities":["hospital 17","hospital 81"]},{"name":"floor 55","amenities":["indoor parking 59"]},{"name":"floor 56","amenities":["pool 33","tennis court 70"]},{"name":"floor 57","amenities":[]},{"name":"floor 58","amenities":["sauna 59"]},{"name":"floor 59","amenities":[]},{"name":"floor 60","amenities":["police station 88"]},{"name":"floor 61","amenities":[]},{"name":"floor 62","amenities":["police station 35"]},{"name":"floor 63","amenities":["heliport 63"]},{"name":"floor 64","amenities":["heliport 36","clinic 67"]},{"name":"floor 65","amenities":["voley court 69"]},{"name":"floor 66","amenities":["grocery store 14"]},{"name":"floor 67","amenities":[]},{"name":"floor 68","amenities":["sauna 61"]},{"name":"floor 69","amenities":["socker court 52"]},{"name":"floor 70","amenities":["football field 40"]},{"name":"floor 71","amenities":[]},{"name":"floor 72","amenities":["socker court 45"]},{"name":"floor 73","amenities":["rest area 51"]},{"name":"floor 74","amenities":["police station 65","pool 77"]},{"name":"floor 75","amenities":["pool 50"]},{"name":"floor 76","amenities":["park 10"]},{"name":"floor 77","amenities":["monkey bars 71","visitor parking 2"]},{"name":"floor 78","amenities":["water slide 94"]},{"name":"floor 79","amenities":[]},{"name":"floor 80","amenities":[]},{"name":"floor 81","amenities":[]},{"name":"floor 82","amenities":["pharmacy 70","indoor parking 10"]},{"name":"floor 83","amenities":["olympic pool 71","visitor parking 9"]},{"name":"floor 84","amenities":["outdoor parking 18"]},{"name":"floor 85","amenities":["voley court 24"]},{"name":"floor 86","amenities":["university 68"]},{"name":"floor 87","amenities":["college 43"]},{"name":"floor 88","amenities":[]},{"name":"floor 89","amenities":["indoor parking 75"]},{"name":"floor 90","amenities":["park 33","super market 46"]},{"name":"floor 91","amenities":["football field 15"]},{"name":"floor 92","amenities":[]},{"name":"floor 93","amenities":["police station 66","water slide 96"]},{"name":"floor 94","amenities":["park 52"]},{"name":"floor 95","amenities":["park 33"]},{"name":"floor 96","amenities":["ice rink 3","jetskis 35"]},{"name":"floor 97","amenities":[]},{"name":"floor 98","amenities":[]},{"name":"floor 99","amenities":["football field 57"]},{"name":"floor 100","amenities":["university 49"]},{"name":"floor 101","amenities":["police station 87"]},{"name":"floor 102","amenities":[]},{"name":"floor 103","amenities":["clinic 48"]},{"name":"floor 104","amenities":[]},{"name":"floor 105","amenities":["monkey bars 11"]},{"name":"floor 106","amenities":["gate 72"]},{"name":"floor 107","amenities":["pharmacy 79","gate 25"]},{"name":"floor 108","amenities":["university 52"]},{"name":"floor 109","amenities":["sauna 66"]},{"name":"floor 110","amenities":["elementary school 11"]},{"name":"floor 111","amenities":["ice rink 95","voley court 29"]},{"name":"floor 112","amenities":["gate 28"]},{"name":"floor 113","amenities":["middle school 56"]},{"name":"floor 114","amenities":["sauna 30"]},{"name":"floor 115","amenities":["heliport 30"]},{"name":"floor 116","amenities":["college 51"]},{"name":"floor 117","amenities":["dog park 79"]},{"name":"floor 118","amenities":["playground 66","gym 63"]},{"name":"floor 119","amenities":["college 48"]},{"name":"floor 120","amenities":[]},{"name":"floor 121","amenities":["football field 38"]},{"name":"floor 122","amenities":["gate 30"]},{"name":"floor 123","amenities":[]},{"name":"floor 124","amenities":["bike parking 54"]},{"name":"floor 125","amenities":["covered parking 33"]},{"name":"floor 126","amenities":[]},{"name":"floor 127","amenities":[]},{"name":"floor 128","amenities":["olympic pool 27"]},{"name":"floor 129","amenities":[]},{"name":"floor 130","amenities":[]},{"name":"floor 131","amenities":["gym 29"]},{"name":"floor 132","amenities":["water slide 61"]},{"name":"floor 133","amenities":["slide 85","park 30"]},{"name":"floor 134","amenities":["gate 39","indoor parking 18"]},{"name":"floor 135","amenities":["hospital 69","outdoor parking 83"]},{"name":"floor 136","amenities":["socker court 35"]},{"name":"floor 137","amenities":[]},{"name":"floor 138","amenities":["heliport 88","dog park 8"]},{"name":"floor 139","amenities":[]},{"name":"floor 140","amenities":["high school 98"]},{"name":"floor 141","amenities":["playground 69","clinic 29"]},{"name":"floor 142","amenities":[]},{"name":"floor 143","amenities":["socker field 32"]},{"name":"floor 144","amenities":["outdoor parking 46"]},{"name":"floor 145","amenities":["dog park 6","grocery store 97"]},{"name":"floor 146","amenities":["market 5","market 61"]},{"name":"floor 147","amenities":["playground 65"]},{"name":"floor 148","amenities":["outdoor parking 86"]},{"name":"floor 149","amenities":["gate 0","grocery store 9"]},{"name":"floor 150","amenities":["hospital 59"]},{"name":"floor 151","amenities":[]},{"name":"floor 152","amenities":[]},{"name":"floor 153","amenities":[]},{"name":"floor 154","amenities":["olympic pool 76"]},{"name":"floor 155","amenities":["middle school 23"]},{"name":"floor 156","amenities":["dog park 3"]},{"name":"floor 157","amenities":["harbor 97","pharmacy 97"]},{"name":"floor 158","amenities":["market 75"]},{"name":"floor 159","amenities":["olympic pool 54"]},{"name":"floor 160","amenities":["police station 48"]},{"name":"floor 161","amenities":["football field 57"]},{"name":"floor 162","amenities":["slide 78","sauna 22"]},{"name":"floor 163","amenities":["covered parking 83"]},{"name":"floor 164","amenities":["indoor parking 7","clinic 48"]},{"name":"floor 165","amenities":["market 29","pharmacy 30"]},{"name":"floor 166","amenities":[]},{"name":"floor 167","amenities":[]},{"name":"floor 168","amenities":["college 66"]},{"name":"floor 169","amenities":["police station 99","gate 69"]},{"name":"floor 170","amenities":["university 56","clinic 66"]},{"name":"floor 171","amenities":[]},{"name":"floor 172","amenities":["playground 99"]},{"name":"floor 173","amenities":[]},{"name":"floor 174","amenities":["harbor 51","olympic pool 54"]},{"name":"floor 175","amenities":[]},{"name":"floor 176","amenities":[]},{"name":"floor 177","amenities":["visitor parking 91"]},{"name":"floor 178","amenities":[]},{"name":"floor 179","amenities":[]},{"name":"floor 180","amenities":["heliport 83"]},{"name":"floor 181","amenities":[]},{"name":"floor 182","amenities":["park 88"]},{"name":"floor 183","amenities":["monkey bars 29","voley court 45"]},{"name":"floor 184","amenities":["super market 95"]},{"name":"floor 185","amenities":["visitor parking 28"]},{"name":"floor 186","amenities":["gym 71"]},{"name":"floor 187","amenities":["rest area 47","gym 32"]},{"name":"floor 188","amenities":[]},{"name":"floor 189","amenities":["bike parking 11"]},{"name":"floor 190","amenities":[]},{"name":"floor 191","amenities":[]},{"name":"floor 192","amenities":["dog park 72","clinic 39"]},{"name":"floor 193","amenities":["olympic pool 0","football field 46"]},{"name":"floor 194","amenities":["curling rink 62"]},{"name":"floor 195","amenities":["bike parking 95"]},{"name":"floor 196","amenities":["elementary school 97"]},{"name":"floor 197","amenities":["playground 19","pharmacy 30"]},{"name":"floor 198","amenities":["bike parking 90","harbor 75"]},{"name":"floor 199","amenities":["grocery store 42"]},{"name":"floor 200","amenities":["grocery store 57"]},{"name":"floor 201","amenities":["water slide 86"]},{"name":"floor 202","amenities":["jetskis 16"]},{"name":"floor 203","amenities":["gym 29"]},{"name":"floor 204","amenities":["football field 59","park 72"]},{"name":"floor 205","amenities":["hospital 81"]},{"name":"floor 206","amenities":[]},{"name":"floor 207","amenities":["super market 80"]},{"name":"floor 208","amenities":["gate 89"]},{"name":"floor 209","amenities":["slide 84"]},{"name":"floor 210","amenities":["socker court 85","college 99"]},{"name":"floor 211","amenities":["market 4"]},{"name":"floor 212","amenities":["slide 28"]},{"name":"floor 213","amenities":["gate 94"]},{"name":"floor 214","amenities":[]},{"name":"floor 215","amenities":["tennis court 12","college 82"]},{"name":"floor 216","amenities":["clinic 38"]},{"name":"floor 217","amenities":[]},{"name":"floor 218","amenities":["college 23","socker field 70"]},{"name":"floor 219","amenities":["pharmacy 67"]},{"name":"floor 220","amenities":[]},{"name":"floor 221","amenities":["heliport 89"]},{"name":"floor 222","amenities":["clinic 31"]},{"name":"floor 223","amenities":["visitor parking 20"]},{"name":"floor 224","amenities":["outdoor parking 61","police station 96"]},{"name":"floor 225","amenities":["gate 62"]},{"name":"floor 226","amenities":[]},{"name":"floor 227","amenities":["park 41"]},{"name":"floor 228","amenities":["olympic pool 36","jetskis 11"]},{"name":"floor 229","amenities":[]},{"name":"floor 230","amenities":["garage 49"]},{"name":"floor 231","amenities":["slide 87"]},{"name":"floor 232","amenities":["ice rink 52"]},{"name":"floor 233","amenities":[]},{"name":"floor 234","amenities":["heliport 34"]},{"name":"floor 235","amenities":["playground 43","tennis court 61"]},{"name":"floor 236","amenities":["super market 56","outdoor parking 58"]},{"name":"floor 237","amenities":[]},{"name":"floor 238","amenities":["elementary school 9","socker court 2"]},{"name":"floor 239","amenities":[]},{"name":"floor 240","amenities":["playground 29","covered parking 31"]},{"name":"floor 241","amenities":["clinic 99"]},{"name":"floor 242","amenities":["hospital 42"]},{"name":"floor 243","amenities":["rest area 19","rest area 87"]},{"name":"floor 244","amenities":[]},{"name":"floor 245","amenities":["socker court 82"]},{"name":"floor 246","amenities":["visitor parking 90","clinic 3"]},{"name":"floor 247","amenities":["indoor parking 57"]},{"name":"floor 248","amenities":["monkey bars 20","gym 40"]},{"name":"floor 249","amenities":["park 16","market 63"]},{"name":"floor 250","amenities":[]},{"name":"floor 251","amenities":["water slide 14"]},{"name":"floor 252","amenities":["heliport 21","pool 91"]},{"name":"floor 253","amenities":["pool 7"]},{"name":"floor 254","amenities":["super market 49"]},{"name":"floor 255","amenities":[]},{"name":"floor 256","amenities":["hospital 5","socker court 22"]},{"name":"floor 257","amenities":["rest area 1"]},{"name":"floor 258","amenities":["voley court 27","park 63"]},{"name":"floor 259","amenities":[]},{"name":"floor 260","amenities":[]},{"name":"floor 261","amenities":["monkey bars 65"]},{"name":"floor 262","amenities":["playground 22"]},{"name":"floor 263","amenities":[]},{"name":"floor 264","amenities":[]},{"name":"floor 265","amenities":["elementary school 82","college 16"]},{"name":"floor 266","amenities":["police station 17"]},{"name":"floor 267","amenities":[]},{"name":"floor 268","amenities":["heliport 70","police station 19"]},{"name":"floor 269","amenities":["park 76","bike parking 43"]},{"name":"floor 270","amenities":["indoor parking 72","bike parking 54"]},{"name":"floor 271","amenities":["visitor parking 83","bike parking 28"]},{"name":"floor 272","amenities":[]},{"name":"floor 273","amenities":["ice rink 5"]},{"name":"floor 274","amenities":["gate 58","outdoor parking 4"]},{"name":"floor 275","amenities":[]},{"name":"floor 276","amenities":["olympic pool 93"]},{"name":"floor 277","amenities":["playground 31","indoor parking 92"]},{"name":"floor 278","amenities":[]},{"name":"floor 279","amenities":["monkey bars 9"]},{"name":"floor 280","amenities":["outdoor parking 7"]},{"name":"floor 281","amenities":["pharmacy 32","football field 22"]},{"name":"floor 282","amenities":["curling rink 36"]},{"name":"floor 283","amenities":["garage 60"]},{"name":"floor 284","amenities":["jetskis 2"]},{"name":"floor 285","amenities":["covered parking 3"]},{"name":"floor 286","amenities":["market 53","pharmacy 67"]},{"name":"floor 287","amenities":["harbor 74"]},{"name":"floor 288","amenities":["ice rink 38"]},{"name":"floor 289","amenities":[]},{"name":"floor 290","amenities":["harbor 58"]},{"name":"floor 291","amenities":["hospital 8","voley court 9"]},{"name":"floor 292","amenities":["bike parking 90"]},{"name":"floor 293","amenities":[]},{"name":"floor 294","amenities":["sauna 68","dog park 10"]},{"name":"floor 295","amenities":["socker field 99","rest area 93"]},{"name":"floor 296","amenities":["playground 22"]},{"name":"floor 297","amenities":["police station 99"]},{"name":"floor 298","amenities":["tennis court 5","pool 42"]},{"name":"floor 299","amenities":["indoor parking 88"]},{"name":"floor 300","amenities":["olympic pool 23"]},{"name":"floor 301","amenities":[]},{"name":"floor 302","amenities":["harbor 78","slide 28"]},{"name":"floor 303","amenities":[]},{"name":"floor 304","amenities":["sauna 76"]},{"name":"floor 305","amenities":["gym 25"]},{"name":"floor 306","amenities":[]},{"name":"floor 307","amenities":[]},{"name":"floor 308","amenities":[]},{"name":"floor 309","amenities":[]},{"name":"floor 310","amenities":["dog park 65"]},{"name":"floor 311","amenities":["outdoor parking 61"]},{"name":"floor 312","amenities":["hospital 6","covered parking 71"]},{"name":"floor 313","amenities":["football field 79"]},{"name":"floor 314","amenities":[]},{"name":"floor 315","amenities":["water slide 82"]},{"name":"floor 316","amenities":["gate 85"]},{"name":"floor 317","amenities":["socker field 65"]},{"name":"floor 318","amenities":[]},{"name":"floor 319","amenities":["curling rink 34","rest area 39"]},{"name":"floor 320","amenities":["visitor parking 65"]},{"name":"floor 321","amenities":["indoor parking 73"]},{"name":"floor 322","amenities":["slide 3"]},{"name":"floor 323","amenities":["middle school 86","pool 29"]},{"name":"floor 324","amenities":["outdoor parking 90"]},{"name":"floor 325","amenities":["playground 61"]},{"name":"floor 326","amenities":["heliport 51"]},{"name":"floor 327","amenities":["super market 96"]},{"name":"floor 328","amenities":[]},{"name":"floor 329","amenities":["university 89"]},{"name":"floor 330","amenities":["pharmacy 76","heliport 57"]},{"name":"floor 331","amenities":[]},{"name":"floor 332","amenities":["hospital 93"]},{"name":"floor 333","amenities":["rest area 2"]},{"name":"floor 334","amenities":[]},{"name":"floor 335","amenities":[]},{"name":"floor 336","amenities":["playground 12"]},{"name":"floor 337","amenities":[]},{"name":"floor 338","amenities":["grocery store 29","socker field 40"]},{"name":"floor 339","amenities":["dog park 53","visitor parking 20"]},{"name":"floor 340","amenities":[]},{"name":"floor 341","amenities":["market 67","dog park 26"]},{"name":"floor 342","amenities":["middle school 20"]},{"name":"floor 343","amenities":["playground 3","super market 30"]},{"name":"floor 344","amenities":["playground 75"]},{"name":"floor 345","amenities":["sauna 5"]},{"name":"floor 346","amenities":["university 4","high school 17"]},{"name":"floor 347","amenities":["elementary school 46"]},{"name":"floor 348","amenities":["visitor parking 53"]},{"name":"floor 349","amenities":["police station 57"]},{"name":"floor 350","amenities":["hospital 99"]},{"name":"floor 351","amenities":["middle school 8"]},{"name":"floor 352","amenities":[]},{"name":"floor 353","amenities":["park 12"]},{"name":"floor 354","amenities":[]},{"name":"floor 355","amenities":[]},{"name":"floor 356","amenities":[]},{"name":"floor 357","amenities":["heliport 61"]},{"name":"floor 358","amenities":[]},{"name":"floor 359","amenities":[]},{"name":"floor 360","amenities":[]},{"name":"floor 361","amenities":["indoor parking 46","grocery store 72"]},{"name":"floor 362","amenities":["market 33"]},{"name":"floor 363","amenities":["olympic pool 53"]},{"name":"floor 364","amenities":["clinic 71"]},{"name":"floor 365","amenities":["socker field 28"]},{"name":"floor 366","amenities":["visitor parking 62","sauna 83"]},{"name":"floor 367","amenities":["grocery store 67","sauna 54"]},{"name":"floor 368","amenities":["pool 7"]},{"name":"floor 369","amenities":["sauna 96"]},{"name":"floor 370","amenities":[]},{"name":"floor 371","amenities":["garage 71"]},{"name":"floor 372","amenities":["high school 79","sauna 32"]},{"name":"floor 373","amenities":[]},{"name":"floor 374","amenities":[]},{"name":"floor 375","amenities":[]},{"name":"floor 376","amenities":["college 2","park 86"]},{"name":"floor 377","amenities":["park 26"]},{"name":"floor 378","amenities":[]},{"name":"floor 379","amenities":["socker court 26","visitor parking 3"]},{"name":"floor 380","amenities":["water slide 89"]},{"name":"floor 381","amenities":[]},{"name":"floor 382","amenities":["slide 39"]},{"name":"floor 383","amenities":["rest area 31"]},{"name":"floor 384","amenities":["college 37"]},{"name":"floor 385","amenities":["pharmacy 22"]},{"name":"floor 386","amenities":[]},{"name":"floor 387","amenities":["pharmacy 8"]},{"name":"floor 388","amenities":["water slide 53","heliport 21"]},{"name":"floor 389","amenities":["middle school 33","jetskis 91"]},{"name":"floor 390","amenities":["indoor parking 44"]},{"name":"floor 391","amenities":["garage 88"]},{"name":"floor 392","amenities":["socker field 88"]},{"name":"floor 393","amenities":["hospital 30","olympic pool 86"]},{"name":"floor 394","amenities":["rest area 58"]},{"name":"floor 395","amenities":["water slide 37"]},{"name":"floor 396","amenities":["elementary school 0"]},{"name":"floor 397","amenities":["football field 13","outdoor parking 2"]},{"name":"floor 398","amenities":["covered parking 71","dog park 53"]},{"name":"floor 399","amenities":["covered parking 72"]},{"name":"floor 400","amenities":["tennis court 61","pool 49"]},{"name":"floor 401","amenities":["market 45"]},{"name":"floor 402","amenities":[]},{"name":"floor 403","amenities":["gym 12"]},{"name":"floor 404","amenities":[]},{"name":"floor 405","amenities":[]},{"name":"floor 406","amenities":["playground 67"]},{"name":"floor 407","amenities":[]},{"name":"floor 408","amenities":["gate 48"]},{"name":"floor 409","amenities":[]},{"name":"floor 410","amenities":["ice rink 2","clinic 24"]},{"name":"floor 411","amenities":["gym 35","outdoor parking 38"]},{"name":"floor 412","amenities":[]},{"name":"floor 413","amenities":[]},{"name":"floor 414","amenities":[]},{"name":"floor 415","amenities":["gate 76"]},{"name":"floor 416","amenities":["elementary school 67","high school 59"]},{"name":"floor 417","amenities":["pool 47"]},{"name":"floor 418","amenities":["visitor parking 98"]},{"name":"floor 419","amenities":["garage 18"]},{"name":"floor 420","amenities":[]},{"name":"floor 421","amenities":["bike parking 34","dog park 27"]},{"name":"floor 422","amenities":["harbor 30"]},{"name":"floor 423","amenities":[]},{"name":"floor 424","amenities":["middle school 15"]},{"name":"floor 425","amenities":[]},{"name":"floor 426","amenities":["grocery store 29","outdoor parking 61"]},{"name":"floor 427","amenities":[]},{"name":"floor 428","amenities":["voley court 69"]},{"name":"floor 429","amenities":["heliport 44"]},{"name":"floor 430","amenities":[]},{"name":"floor 431","amenities":["bike parking 35"]},{"name":"floor 432","amenities":["hospital 47","hospital 93"]},{"name":"floor 433","amenities":[]},{"name":"floor 434","amenities":["police station 21"]},{"name":"floor 435","amenities":[]},{"name":"floor 436","amenities":["socker field 24"]},{"name":"floor 437","amenities":[]},{"name":"floor 438","amenities":["curling rink 22","gate 53"]},{"name":"floor 439","amenities":["pool 65","rest area 97"]},{"name":"floor 440","amenities":[]},{"name":"floor 441","amenities":["ice rink 92","olympic pool 11"]},{"name":"floor 442","amenities":[]},{"name":"floor 443","amenities":["covered parking 52"]},{"name":"floor 444","amenities":["college 84"]},{"name":"floor 445","amenities":["sauna 29","grocery store 30"]},{"name":"floor 446","amenities":[]},{"name":"floor 447","amenities":["elementary school 35","college 71"]},{"name":"floor 448","amenities":["harbor 54","olympic pool 57"]},{"name":"floor 449","amenities":["pharmacy 31","curling rink 13"]},{"name":"floor 450","amenities":["ice rink 27"]},{"name":"floor 451","amenities":[]},{"name":"floor 452","amenities":["middle school 48"]},{"name":"floor 453","amenities":["market 90","dog park 1"]},{"name":"floor 454","amenities":["pharmacy 49"]},{"name":"floor 455","amenities":["socker field 33"]},{"name":"floor 456","amenities":["middle school 36"]},{"name":"floor 457","amenities":["pool 98"]},{"name":"floor 458","amenities":["elementary school 43"]},{"name":"floor 459","amenities":["outdoor parking 4","police station 76"]},{"name":"floor 460","amenities":[]},{"name":"floor 461","amenities":["playground 14"]},{"name":"floor 462","amenities":["jetskis 77","super market 42"]},{"name":"floor 463","amenities":[]},{"name":"floor 464","amenities":["gate 29"]},{"name":"floor 465","amenities":["hospital 87"]},{"name":"floor 466","amenities":[]},{"name":"floor 467","amenities":["rest area 89"]},{"name":"floor 468","amenities":["ice rink 15"]},{"name":"floor 469","amenities":["elementary school 93"]},{"name":"floor 470","amenities":[]},{"name":"floor 471","amenities":[]},{"name":"floor 472","amenities":["super market 19"]},{"name":"floor 473","amenities":["pool 29"]},{"name":"floor 474","amenities":["heliport 85","slide 41"]},{"name":"floor 475","amenities":["harbor 95","olympic pool 67"]},{"name":"floor 476","amenities":["pharmacy 8"]},{"name":"floor 477","amenities":["harbor 64","water slide 89"]},{"name":"floor 478","amenities":["clinic 34"]},{"name":"floor 479","amenities":["high school 21","curling rink 75"]},{"name":"floor 480","amenities":["clinic 48"]},{"name":"floor 481","amenities":["sauna 90"]},{"name":"floor 482","amenities":[]},{"name":"floor 483","amenities":[]},{"name":"floor 484","amenities":[]},{"name":"floor 485","amenities":["sauna 49","covered parking 18"]},{"name":"floor 486","amenities":["gate 30"]},{"name":"floor 487","amenities":["jetskis 7"]},{"name":"floor 488","amenities":["harbor 59"]},{"name":"floor 489","amenities":["socker field 53"]},{"name":"floor 490","amenities":["heliport 83","grocery store 87"]},{"name":"floor 491","amenities":["pharmacy 50","super market 7"]},{"name":"floor 492","amenities":["super market 99"]},{"name":"floor 493","amenities":["covered parking 47"]},{"name":"floor 494","amenities":[]},{"name":"floor 495","amenities":[]},{"name":"floor 496","amenities":[]},{"name":"floor 497","amenities":["olympic pool 24","high school 3"]},{"name":"floor 498","amenities":["gym 51","garage 12"]},{"name":"floor 499","amenities":["gym 49","park 21"]},{"name":"floor 500","amenities":["garage 78"]},{"name":"floor 501","amenities":["covered parking 97","football field 56"]},{"name":"floor 502","amenities":["clinic 66","garage 0"]},{"name":"floor 503","amenities":[]},{"name":"floor 504","amenities":[]},{"name":"floor 505","amenities":[]},{"name":"floor 506","amenities":["socker court 78"]},{"name":"floor 507","amenities":["socker court 34","slide 90"]},{"name":"floor 508","amenities":["heliport 32","university 82"]},{"name":"floor 509","amenities":["ice rink 81"]},{"name":"floor 510","amenities":["jetskis 51","harbor 44"]},{"name":"floor 511","amenities":[]},{"name":"floor 512","amenities":[]},{"name":"floor 513","amenities":[]},{"name":"floor 514","amenities":["sauna 18"]},{"name":"floor 515","amenities":[]},{"name":"floor 516","amenities":["slide 29","gym 23"]},{"name":"floor 517","amenities":["visitor parking 31","college 5"]},{"name":"floor 518","amenities":["harbor 53"]},{"name":"floor 519","amenities":["playground 44"]},{"name":"floor 520","amenities":[]},{"name":"floor 521","amenities":[]},{"name":"floor 522","amenities":["garage 84"]},{"name":"floor 523","amenities":[]},{"name":"floor 524","amenities":["clinic 33"]},{"name":"floor 525","amenities":["rest area 72"]},{"name":"floor 526","amenities":["pool 83"]},{"name":"floor 527","amenities":["rest area 35"]},{"name":"floor 528","amenities":["slide 76"]},{"name":"floor 529","amenities":["bike parking 20"]},{"name":"floor 530","amenities":["socker field 54","super market 25"]},{"name":"floor 531","amenities":["high school 76"]},{"name":"floor 532","amenities":[]},{"name":"floor 533","amenities":["curling rink 74"]},{"name":"floor 534","amenities":[]},{"name":"floor 535","amenities":["playground 90"]},{"name":"floor 536","amenities":["college 23"]},{"name":"floor 537","amenities":["grocery store 75","ice rink 8"]},{"name":"floor 538","amenities":["socker court 73"]},{"name":"floor 539","amenities":["harbor 98","monkey bars 57"]},{"name":"floor 540","amenities":["pharmacy 53"]},{"name":"floor 541","amenities":["water slide 46"]},{"name":"floor 542","amenities":["elementary school 14"]},{"name":"floor 543","amenities":["university 50","gym 90"]},{"name":"floor 544","amenities":["hospital 5"]},{"name":"floor 545","amenities":["park 95"]},{"name":"floor 546","amenities":["clinic 61"]},{"name":"floor 547","amenities":["socker field 16","bike parking 21"]},{"name":"floor 548","amenities":["high school 75"]},{"name":"floor 549","amenities":["grocery store 90","outdoor parking 10"]},{"name":"floor 550","amenities":[]},{"name":"floor 551","amenities":["high school 26"]},{"name":"floor 552","amenities":[]},{"name":"floor 553","amenities":[]},{"name":"floor 554","amenities":["harbor 39","police station 98"]},{"name":"floor 555","amenities":["socker field 65"]},{"name":"floor 556","amenities":["elementary school 18"]},{"name":"floor 557","amenities":["olympic pool 59"]},{"name":"floor 558","amenities":["grocery store 46"]},{"name":"floor 559","amenities":["tennis court 83","olympic pool 25"]},{"name":"floor 560","amenities":[]},{"name":"floor 561","amenities":["park 0"]},{"name":"floor 562","amenities":[]},{"name":"floor 563","amenities":["monkey bars 12"]},{"name":"floor 564","amenities":[]},{"name":"floor 565","amenities":["pool 17"]},{"name":"floor 566","amenities":["super market 95"]},{"name":"floor 567","amenities":[]},{"name":"floor 568","amenities":["harbor 14"]},{"name":"floor 569","amenities":["socker field 28","covered parking 38"]},{"name":"floor 570","amenities":["bike parking 55"]},{"name":"floor 571","amenities":["harbor 28","harbor 12"]},{"name":"floor 572","amenities":["police station 92"]},{"name":"floor 573","amenities":["pool 94","football field 78"]},{"name":"floor 574","amenities":["bike parking 85"]},{"name":"floor 575","amenities":["playground 68"]},{"name":"floor 576","amenities":["jetskis 34"]},{"name":"floor 577","amenities":["jetskis 46"]},{"name":"floor 578","amenities":["tennis court 92"]},{"name":"floor 579","amenities":["visitor parking 81"]},{"name":"floor 580","amenities":["pool 50"]},{"name":"floor 581","amenities":["market 23"]},{"name":"floor 582","amenities":["football field 82"]},{"name":"floor 583","amenities":["socker court 63"]},{"name":"floor 584","amenities":[]},{"name":"floor 585","amenities":["market 66"]},{"name":"floor 586","amenities":[]},{"name":"floor 587","amenities":["college 61"]},{"name":"floor 588","amenities":["pharmacy 62"]},{"name":"floor 589","amenities":["police station 78"]},{"name":"floor 590","amenities":[]},{"name":"floor 591","amenities":["monkey bars 26"]},{"name":"floor 592","amenities":["jetskis 4"]},{"name":"floor 593","amenities":["police station 27","ice rink 27"]},{"name":"floor 594","amenities":[]},{"name":"floor 595","amenities":["gym 90"]},{"name":"floor 596","amenities":["garage 52"]},{"name":"floor 597","amenities":["water slide 55"]},{"name":"floor 598","amenities":["harbor 36"]},{"name":"floor 599","amenities":[]},{"name":"floor 600","amenities":["harbor 63","middle school 33"]},{"name":"floor 601","amenities":["voley court 31"]},{"name":"floor 602","amenities":["socker field 64"]},{"name":"floor 603","amenities":["garage 69"]},{"name":"floor 604","amenities":[]},{"name":"floor 605","amenities":["pool 26"]},{"name":"floor 606","amenities":["socker court 47","park 95"]},{"name":"floor 607","amenities":["slide 24","socker court 49"]},{"name":"floor 608","amenities":["socker court 24"]},{"name":"floor 609","amenities":["garage 99"]},{"name":"floor 610","amenities":["middle school 90"]},{"name":"floor 611","amenities":["indoor parking 14"]},{"name":"floor 612","amenities":[]},{"name":"floor 613","amenities":[]},{"name":"floor 614","amenities":["monkey bars 79","dog park 54"]},{"name":"floor 615","amenities":["pool 24"]},{"name":"floor 616","amenities":["heliport 15"]},{"name":"floor 617","amenities":["jetskis 87","voley court 25"]},{"name":"floor 618","amenities":[]},{"name":"floor 619","amenities":[]},{"name":"floor 620","amenities":["police station 83"]},{"name":"floor 621","amenities":["market 98","market 58"]},{"name":"floor 622","amenities":["dog park 49"]},{"name":"floor 623","amenities":["gym 17"]},{"name":"floor 624","amenities":["football field 0","university 97"]},{"name":"floor 625","amenities":[]},{"name":"floor 626","amenities":["olympic pool 44"]},{"name":"floor 627","amenities":["pool 42"]},{"name":"floor 628","amenities":["hospital 90"]},{"name":"floor 629","amenities":[]},{"name":"floor 630","amenities":["bike parking 33"]},{"name":"floor 631","amenities":["pool 86"]},{"name":"floor 632","amenities":["pharmacy 28"]},{"name":"floor 633","amenities":["dog park 92"]},{"name":"floor 634","amenities":[]},{"name":"floor 635","amenities":[]},{"name":"floor 636","amenities":["rest area 88"]},{"name":"floor 637","amenities":["socker court 40"]},{"name":"floor 638","amenities":["monkey bars 29"]},{"name":"floor 639","amenities":["garage 77","pool 45"]},{"name":"floor 640","amenities":["heliport 55"]},{"name":"floor 641","amenities":["socker court 8"]},{"name":"floor 642","amenities":["socker field 20"]},{"name":"floor 643","amenities":[]},{"name":"floor 644","amenities":[]},{"name":"floor 645","amenities":["visitor parking 97","rest area 95"]},{"name":"floor 646","amenities":["sauna 26"]},{"name":"floor 647","amenities":[]},{"name":"floor 648","amenities":["grocery store 0"]},{"name":"floor 649","amenities":["outdoor parking 58"]},{"name":"floor 650","amenities":["covered parking 65"]},{"name":"floor 651","amenities":[]},{"name":"floor 652","amenities":["hospital 18","super market 10"]},{"name":"floor 653","amenities":["ice rink 76","grocery store 84"]},{"name":"floor 654","amenities":["pharmacy 50"]},{"name":"floor 655","amenities":["dog park 74"]},{"name":"floor 656","amenities":[]},{"name":"floor 657","amenities":["jetskis 74"]},{"name":"floor 658","amenities":["jetskis 69","curling rink 26"]},{"name":"floor 659","amenities":["slide 38","heliport 7"]},{"name":"floor 660","amenities":["university 93"]},{"name":"floor 661","amenities":["voley court 45"]},{"name":"floor 662","amenities":["harbor 0"]},{"name":"floor 663","amenities":["visitor parking 59","football field 89"]},{"name":"floor 664","amenities":[]},{"name":"floor 665","amenities":[]},{"name":"floor 666","amenities":[]},{"name":"floor 667","amenities":[]},{"name":"floor 668","amenities":[]},{"name":"floor 669","amenities":[]},{"name":"floor 670","amenities":["market 64","hospital 83"]},{"name":"floor 671","amenities":["gym 73","sauna 24"]},{"name":"floor 672","amenities":[]},{"name":"floor 673","amenities":["ice rink 32"]},{"name":"floor 674","amenities":["harbor 17"]},{"name":"floor 675","amenities":[]},{"name":"floor 676","amenities":["socker field 12"]},{"name":"floor 677","amenities":["tennis court 82"]},{"name":"floor 678","amenities":[]},{"name":"floor 679","amenities":["slide 71"]},{"name":"floor 680","amenities":[]},{"name":"floor 681","amenities":["gate 13"]},{"name":"floor 682","amenities":[]},{"name":"floor 683","amenities":[]},{"name":"floor 684","amenities":["heliport 77","voley court 0"]},{"name":"floor 685","amenities":["curling rink 16"]},{"name":"floor 686","amenities":[]},{"name":"floor 687","amenities":[]},{"name":"floor 688","amenities":[]},{"name":"floor 689","amenities":[]},{"name":"floor 690","amenities":["tennis court 96"]},{"name":"floor 691","amenities":["slide 58","hospital 14"]},{"name":"floor 692","amenities":["ice rink 72"]},{"name":"floor 693","amenities":["harbor 24","clinic 69"]},{"name":"floor 694","amenities":[]},{"name":"floor 695","amenities":[]},{"name":"floor 696","amenities":["ice rink 14"]},{"name":"floor 697","amenities":["playground 83"]},{"name":"floor 698","amenities":["outdoor parking 95"]},{"name":"floor 699","amenities":["gym 48"]},{"name":"floor 700","amenities":[]},{"name":"floor 701","amenities":["university 12"]},{"name":"floor 702","amenities":["middle school 13"]},{"name":"floor 703","amenities":["socker court 44","outdoor parking 97"]},{"name":"floor 704","amenities":["monkey bars 62"]},{"name":"floor 705","amenities":[]},{"name":"floor 706","amenities":["university 5"]},{"name":"floor 707","amenities":["curling rink 5","middle school 32"]},{"name":"floor 708","amenities":[]},{"name":"floor 709","amenities":["curling rink 42"]},{"name":"floor 710","amenities":["tennis court 4","ice rink 3"]},{"name":"floor 711","amenities":["dog park 12"]},{"name":"floor 712","amenities":["socker field 66","park 34"]},{"name":"floor 713","amenities":[]},{"name":"floor 714","amenities":["football field 70","socker court 72"]},{"name":"floor 715","amenities":["pharmacy 35"]},{"name":"floor 716","amenities":["elementary school 87","dog park 49"]},{"name":"floor 717","amenities":["hospital 50"]},{"name":"floor 718","amenities":["tennis court 38"]},{"name":"floor 719","amenities":["socker court 98"]},{"name":"floor 720","amenities":["university 5"]},{"name":"floor 721","amenities":["covered parking 64","super market 45"]},{"name":"floor 722","amenities":["playground 89","ice rink 28"]},{"name":"floor 723","amenities":[]},{"name":"floor 724","amenities":["tennis court 33","dog park 89"]},{"name":"floor 725","amenities":[]},{"name":"floor 726","amenities":["outdoor parking 58"]},{"name":"floor 727","amenities":["gym 11"]},{"name":"floor 728","amenities":["garage 95"]},{"name":"floor 729","amenities":[]},{"name":"floor 730","amenities":["heliport 54"]},{"name":"floor 731","amenities":[]},{"name":"floor 732","amenities":["water slide 14","dog park 92"]},{"name":"floor 733","amenities":[]},{"name":"floor 734","amenities":["visitor parking 94"]},{"name":"floor 735","amenities":[]},{"name":"floor 736","amenities":[]},{"name":"floor 737","amenities":["slide 41"]},{"name":"floor 738","amenities":[]},{"name":"floor 739","amenities":["bike parking 53"]},{"name":"floor 740","amenities":["super market 53"]},{"name":"floor 741","amenities":["pool 16","slide 29"]},{"name":"floor 742","amenities":["tennis court 45","ice rink 89"]},{"name":"floor 743","amenities":["water slide 26"]},{"name":"floor 744","amenities":["water slide 69"]},{"name":"floor 745","amenities":["outdoor parking 94"]},{"name":"floor 746","amenities":["gate 5"]},{"name":"floor 747","amenities":["gym 59","water slide 36"]},{"name":"floor 748","amenities":["super market 87"]},{"name":"floor 749","amenities":["pharmacy 40","dog park 51"]},{"name":"floor 750","amenities":["outdoor parking 48"]},{"name":"floor 751","amenities":["indoor parking 64"]},{"name":"floor 752","amenities":["heliport 92","garage 98"]},{"name":"floor 753","amenities":["dog park 69"]},{"name":"floor 754","amenities":["bike parking 0"]},{"name":"floor 755","amenities":[]},{"name":"floor 756","amenities":[]},{"name":"floor 757","amenities":["tennis court 73","clinic 82"]},{"name":"floor 758","amenities":["pool 93"]},{"name":"floor 759","amenities":["park 65"]},{"name":"floor 760","amenities":["dog park 88"]},{"name":"floor 761","amenities":[]},{"name":"floor 762","amenities":["pool 33"]},{"name":"floor 763","amenities":[]},{"name":"floor 764","amenities":[]},{"name":"floor 765","amenities":["indoor parking 90"]},{"name":"floor 766","amenities":["socker field 17"]},{"name":"floor 767","amenities":["monkey bars 33"]},{"name":"floor 768","amenities":["park 75"]},{"name":"floor 769","amenities":["voley court 83"]},{"name":"floor 770","amenities":[]},{"name":"floor 771","amenities":[]},{"name":"floor 772","amenities":["clinic 52"]},{"name":"floor 773","amenities":[]},{"name":"floor 774","amenities":["grocery store 40"]},{"name":"floor 775","amenities":["university 59"]},{"name":"floor 776","amenities":["pool 11","park 92"]},{"name":"floor 777","amenities":[]},{"name":"floor 778","amenities":["high school 27","gym 3"]},{"name":"floor 779","amenities":[]},{"name":"floor 780","amenities":["dog park 76"]},{"name":"floor 781","amenities":["tennis court 85"]},{"name":"floor 782","amenities":["grocery store 46"]},{"name":"floor 783","amenities":[]},{"name":"floor 784","amenities":["water slide 44"]},{"name":"floor 785","amenities":["football field 38"]},{"name":"floor 786","amenities":["bike parking 98","playground 21"]},{"name":"floor 787","amenities":[]},{"name":"floor 788","amenities":["jetskis 1","dog park 31"]},{"name":"floor 789","amenities":[]},{"name":"floor 790","amenities":["market 21"]},{"name":"floor 791","amenities":["hospital 23"]},{"name":"floor 792","amenities":["outdoor parking 17","gym 8"]},{"name":"floor 793","amenities":["pharmacy 22","university 89"]},{"name":"floor 794","amenities":["water slide 73"]},{"name":"floor 795","amenities":["monkey bars 67"]},{"name":"floor 796","amenities":["playground 16"]},{"name":"floor 797","amenities":["indoor parking 64","slide 0"]},{"name":"floor 798","amenities":["curling rink 49"]},{"name":"floor 799","amenities":["covered parking 7"]},{"name":"floor 800","amenities":["outdoor parking 4","pharmacy 31"]},{"name":"floor 801","amenities":["monkey bars 69"]},{"name":"floor 802","amenities":["elementary school 52"]},{"name":"floor 803","amenities":["covered parking 79"]},{"name":"floor 804","amenities":["outdoor parking 19"]},{"name":"floor 805","amenities":["football field 37"]},{"name":"floor 806","amenities":[]},{"name":"floor 807","amenities":["ice rink 81","monkey bars 80"]},{"name":"floor 808","amenities":["grocery store 45","harbor 95"]},{"name":"floor 809","amenities":["garage 89"]},{"name":"floor 810","amenities":["jetskis 27"]},{"name":"floor 811","amenities":["market 71"]},{"name":"floor 812","amenities":["visitor parking 72","park 65"]},{"name":"floor 813","amenities":["slide 40"]},{"name":"floor 814","amenities":[]},{"name":"floor 815","amenities":[]},{"name":"floor 816","amenities":["ice rink 9"]},{"name":"floor 817","amenities":[]},{"name":"floor 818","amenities":["hospital 63"]},{"name":"floor 819","amenities":["grocery store 42"]},{"name":"floor 820","amenities":["curling rink 15","outdoor parking 47"]},{"name":"floor 821","amenities":["super market 62"]},{"name":"floor 822","amenities":["socker court 17","outdoor parking 66"]},{"name":"floor 823","amenities":["curling rink 7"]},{"name":"floor 824","amenities":["elementary school 4"]},{"name":"floor 825","amenities":["ice rink 96"]},{"name":"floor 826","amenities":["tennis court 69"]},{"name":"floor 827","amenities":["hospital 28"]},{"name":"floor 828","amenities":["middle school 81"]},{"name":"floor 829","amenities":["olympic pool 25"]},{"name":"floor 830","amenities":["pharmacy 36"]},{"name":"floor 831","amenities":["middle school 57"]},{"name":"floor 832","amenities":["grocery store 62","dog park 14"]},{"name":"floor 833","amenities":["covered parking 33","market 98"]},{"name":"floor 834","amenities":["olympic pool 76"]},{"name":"floor 835","amenities":["socker field 95","olympic pool 10"]},{"name":"floor 836","amenities":["socker field 11"]},{"name":"floor 837","amenities":["water slide 57","water slide 16"]},{"name":"floor 838","amenities":["socker court 78"]},{"name":"floor 839","amenities":["slide 15"]},{"name":"floor 840","amenities":["outdoor parking 0","playground 56"]},{"name":"floor 841","amenities":["grocery store 82","gym 97"]},{"name":"floor 842","amenities":["harbor 2"]},{"name":"floor 843","amenities":["garage 42","market 28"]},{"name":"floor 844","amenities":["elementary school 62"]},{"name":"floor 845","amenities":["bike parking 92","dog park 65"]},{"name":"floor 846","amenities":["socker court 2","garage 20"]},{"name":"floor 847","amenities":["indoor parking 34","playground 73"]},{"name":"floor 848","amenities":["super market 3"]},{"name":"floor 849","amenities":["curling rink 93"]},{"name":"floor 850","amenities":["heliport 33","bike parking 22"]},{"name":"floor 851","amenities":["socker field 21"]},{"name":"floor 852","amenities":["rest area 89"]},{"name":"floor 853","amenities":["socker field 74","sauna 23"]},{"name":"floor 854","amenities":["gym 35"]},{"name":"floor 855","amenities":["jetskis 54","college 49"]},{"name":"floor 856","amenities":["pool 25"]},{"name":"floor 857","amenities":["gym 19"]},{"name":"floor 858","amenities":["super market 3","tennis court 35"]},{"name":"floor 859","amenities":["middle school 14"]},{"name":"floor 860","amenities":["visitor parking 3","pharmacy 25"]},{"name":"floor 861","amenities":["harbor 32"]},{"name":"floor 862","amenities":["heliport 89","socker court 69"]},{"name":"floor 863","amenities":["socker court 51"]},{"name":"floor 864","amenities":["football field 31"]},{"name":"floor 865","amenities":[]},{"name":"floor 866","amenities":[]},{"name":"floor 867","amenities":[]},{"name":"floor 868","amenities":["slide 75"]},{"name":"floor 869","amenities":["slide 53","market 25"]},{"name":"floor 870","amenities":["market 46"]},{"name":"floor 871","amenities":["police station 46"]},{"name":"floor 872","amenities":["rest area 26"]},{"name":"floor 873","amenities":[]},{"name":"floor 874","amenities":[]},{"name":"floor 875","amenities":[]},{"name":"floor 876","amenities":["tennis court 49"]},{"name":"floor 877","amenities":[]},{"name":"floor 878","amenities":["curling rink 64"]},{"name":"floor 879","amenities":["olympic pool 53","visitor parking 67"]},{"name":"floor 880","amenities":["college 47","olympic pool 9"]},{"name":"floor 881","amenities":["bike parking 52"]},{"name":"floor 882","amenities":[]},{"name":"floor 883","amenities":["garage 71","slide 7"]},{"name":"floor 884","amenities":[]},{"name":"floor 885","amenities":["jetskis 67","garage 33"]},{"name":"floor 886","amenities":[]},{"name":"floor 887","amenities":["police station 13"]},{"name":"floor 888","amenities":["socker court 22"]},{"name":"floor 889","amenities":[]},{"name":"floor 890","amenities":["tennis court 81"]},{"name":"floor 891","amenities":["grocery store 83","park 31"]},{"name":"floor 892","amenities":[]},{"name":"floor 893","amenities":["indoor parking 27","garage 23"]},{"name":"floor 894","amenities":["indoor parking 40"]},{"name":"floor 895","amenities":["elementary school 47"]},{"name":"floor 896","amenities":["super market 98"]},{"name":"floor 897","amenities":["jetskis 74"]},{"name":"floor 898","amenities":["garage 30","market 24"]},{"name":"floor 899","amenities":["dog park 65","grocery store 3"]},{"name":"floor 900","amenities":["middle school 92","park 54"]},{"name":"floor 901","amenities":["playground 12","harbor 6"]},{"name":"floor 902","amenities":["socker court 54","slide 58"]},{"name":"floor 903","amenities":["gym 89","socker field 95"]},{"name":"floor 904","amenities":["jetskis 63","high school 95"]},{"name":"floor 905","amenities":["rest area 27"]},{"name":"floor 906","amenities":["college 71"]},{"name":"floor 907","amenities":["park 3"]},{"name":"floor 908","amenities":[]},{"name":"floor 909","amenities":["visitor parking 47"]},{"name":"floor 910","amenities":[]},{"name":"floor 911","amenities":["hospital 1"]},{"name":"floor 912","amenities":["outdoor parking 10"]},{"name":"floor 913","amenities":["pool 96","bike parking 50"]},{"name":"floor 914","amenities":["olympic pool 54","socker court 48"]},{"name":"floor 915","amenities":["bike parking 65"]},{"name":"floor 916","amenities":["college 68"]},{"name":"floor 917","amenities":["outdoor parking 0"]},{"name":"floor 918","amenities":["water slide 74"]},{"name":"floor 919","amenities":["ice rink 92","harbor 1"]},{"name":"floor 920","amenities":["pharmacy 98","gate 64"]},{"name":"floor 921","amenities":["elementary school 10"]},{"name":"floor 922","amenities":[]},{"name":"floor 923","amenities":[]},{"name":"floor 924","amenities":["pool 96","grocery store 74"]},{"name":"floor 925","amenities":["pharmacy 3"]},{"name":"floor 926","amenities":["jetskis 20","socker court 1"]},{"name":"floor 927","amenities":[]},{"name":"floor 928","amenities":["garage 14"]},{"name":"floor 929","amenities":["high school 82"]},{"name":"floor 930","amenities":["indoor parking 17","sauna 62"]},{"name":"floor 931","amenities":["garage 16","market 78"]},{"name":"floor 932","amenities":[]},{"name":"floor 933","amenities":["college 20"]},{"name":"floor 934","amenities":[]},{"name":"floor 935","amenities":["grocery store 31"]},{"name":"floor 936","amenities":["heliport 67","olympic pool 90"]},{"name":"floor 937","amenities":["college 77"]},{"name":"floor 938","amenities":["curling rink 20"]},{"name":"floor 939","amenities":["visitor parking 15"]},{"name":"floor 940","amenities":["police station 63","police station 97"]},{"name":"floor 941","amenities":["college 88"]},{"name":"floor 942","amenities":["socker field 78"]},{"name":"floor 943","amenities":["voley court 88"]},{"name":"floor 944","amenities":["jetskis 20","super market 15"]},{"name":"floor 945","amenities":["socker field 50","college 91"]},{"name":"floor 946","amenities":["curling rink 36","sauna 24"]},{"name":"floor 947","amenities":["market 18"]},{"name":"floor 948","amenities":["water slide 7"]},{"name":"floor 949","amenities":["olympic pool 37","park 87"]},{"name":"floor 950","amenities":["grocery store 83","middle school 63"]},{"name":"floor 951","amenities":["slide 53"]},{"name":"floor 952","amenities":["football field 47"]},{"name":"floor 953","amenities":[]},{"name":"floor 954","amenities":["socker field 82"]},{"name":"floor 955","amenities":["college 34","heliport 5"]},{"name":"floor 956","amenities":["rest area 78"]},{"name":"floor 957","amenities":["sauna 10","pool 93"]},{"name":"floor 958","amenities":[]},{"name":"floor 959","amenities":["pharmacy 90","college 69"]},{"name":"floor 960","amenities":[]},{"name":"floor 961","amenities":[]},{"name":"floor 962","amenities":["garage 6"]},{"name":"floor 963","amenities":["visitor parking 89"]},{"name":"floor 964","amenities":["monkey bars 48"]},{"name":"floor 965","amenities":["middle school 95"]},{"name":"floor 966","amenities":[]},{"name":"floor 967","amenities":["university 52"]},{"name":"floor 968","amenities":["sauna 91"]},{"name":"floor 969","amenities":["police station 37"]},{"name":"floor 970","amenities":[]},{"name":"floor 971","amenities":["college 82"]},{"name":"floor 972","amenities":["university 63"]},{"name":"floor 973","amenities":[]},{"name":"floor 974","amenities":["heliport 79"]},{"name":"floor 975","amenities":["garage 20"]},{"name":"floor 976","amenities":["voley court 27"]},{"name":"floor 977","amenities":["college 68"]},{"name":"floor 978","amenities":[]},{"name":"floor 979","amenities":[]},{"name":"floor 980","amenities":["curling rink 15"]},{"name":"floor 981","amenities":["curling rink 17"]},{"name":"floor 982","amenities":["super market 16"]},{"name":"floor 983","amenities":["police station 42","visitor parking 62"]},{"name":"floor 984","amenities":["high school 2"]},{"name":"floor 985","amenities":["socker field 28","pool 97"]},{"name":"floor 986","amenities":[]},{"name":"floor 987","amenities":["park 71"]},{"name":"floor 988","amenities":["heliport 4","water slide 74"]},{"name":"floor 989","amenities":[]},{"name":"floor 990","amenities":[]},{"name":"floor 991","amenities":["socker court 7","middle school 94"]},{"name":"floor 992","amenities":["gate 38","sauna 12"]},{"name":"floor 993","amenities":["indoor parking 9","hospital 68"]},{"name":"floor 994","amenities":[]},{"name":"floor 995","amenities":[]},{"name":"floor 996","amenities":["gate 38"]},{"name":"floor 997","amenities":[]},{"name":"floor 998","amenities":["college 30"]},{"name":"floor 999","amenities":["high school 2"]},{"name":"floor 1000","amenities":["sauna 6"]}]